fish2pano.libs/libgomp-d22c30c5.so.1.0.0
fish2pano/fast.c
fish2pano/fast.py
fish2pano/__init__.py
fish2pano/fast.cpython-311-aarch64-linux-gnu.so
fish2pano/tests/__init__.py
fish2pano-0.4.1.dist-info/LICENSE
fish2pano-0.4.1.dist-info/AUTHORS
fish2pano-0.4.1.dist-info/WHEEL
fish2pano-0.4.1.dist-info/METADATA
fish2pano-0.4.1.dist-info/top_level.txt
fish2pano-0.4.1.dist-info/RECORD
