Metadata-Version: 2.1
Name: fish2pano
Version: 0.4.1
Summary: A library to convert numpy fisheye images to panoramic.
Author-email: Russell Valentine <russell.valentine@gmail.com>
Project-URL: Homepage, https://github.com/bluthen/fish2pano
Project-URL: Issues, https://github.com/bluthen/fish2pano/issues
Classifier: Programming Language :: Python :: 3
Classifier: License :: CC0 1.0 Universal (CC0 1.0) Public Domain Dedication
Classifier: Operating System :: OS Independent
Requires-Python: >=3.7
License-File: LICENSE
License-File: AUTHORS
Requires-Dist: numpy
